damqt6/__init__.py
damqt6/_common.py
damqt6/_qapplication.py
damqt6/_qbuttons.py
damqt6/_qcomboboxes.py
damqt6/_qdialogs.py
damqt6/_qlabels.py
damqt6/_qlineedits.py
damqt6/_qlistwidgets.py
damqt6/_qsignals.py
damqt6/_qtablewidgets.py
damqt6/_qvalidators.py
damqt6/_qwindows.py
damqt6/_settings.py
damqt6/debug.py
damqt6-0.7.15.dist-info/LICENSE
damqt6-0.7.15.dist-info/METADATA
damqt6-0.7.15.dist-info/WHEEL
damqt6-0.7.15.dist-info/top_level.txt
damqt6-0.7.15.dist-info/RECORD
