Metadata-Version: 2.1
Name: damqt6
Version: 0.7.15
Summary: Dahmaloch's PyQt6 controls
Author-email: Dahmaloch <dahmaloch@gmail.com>
Classifier: Programming Language :: Python :: 3
Classifier: License :: OSI Approved :: MIT License
Classifier: Operating System :: OS Independent
Requires-Python: >=3.10
License-File: LICENSE
Requires-Dist: PyQt6 (==6.4.2)
Requires-Dist: PyQt6-Qt6 (==6.4.2)
Requires-Dist: PyQt6-sip (==13.5.1)
Requires-Dist: damstrings (>=0.7.2)
